mhyt/__init__.py
mhyt-3.5.5.dist-info/METADATA
mhyt-3.5.5.dist-info/WHEEL
mhyt-3.5.5.dist-info/top_level.txt
mhyt-3.5.5.dist-info/RECORD
