Metadata-Version: 2.1
Name: mhyt
Version: 3.5.5
Summary: download files from youtube using simple code
Home-page: https://github.com/matan-h/mhyt
Author: matan h
Author-email: matan.honig2@gmail.com
License: MIT
Platform: UNKNOWN
Classifier: Programming Language :: Python :: 3
Classifier: License :: OSI Approved :: MIT License
Classifier: Operating System :: OS Independent
Requires-Python: >=3.0
